license.S.HTML
venue.S.HTML
volts/___itinerary/itinerary.S.HTML
volts/___itinerary/maybes.s.HTML
volts/___itinerary/processes/errout/script.py
volts/___itinerary/processes/errout/start.py
volts/___itinerary/processes/errout_v1/script.py
volts/___itinerary/processes/errout_v1/start.py
volts/___itinerary/processes/errout_v2/script.py
volts/___itinerary/processes/errout_v2/start.py
volts/__bin/volts_1
volts/__init__.py
volts/__license/options/gpl-3.0-standalone.html
volts/_book/advanced tutorial.s.HTML
volts/_book/book.s.HTML
volts/_book/example output.s.HTML
volts/_book/relevant.s.HTML
volts/_clique/__init__.py
volts/_clique/group/__init__.py
volts/_status/--statuspy.py
volts/_status/DB/records.json
volts/_status/establish.py
volts/_status/monitors/-1_start/chassis/modules/monitor_1.py
volts/_status/monitors/-1_start/status_1.py
volts/_status/monitors/0_start/chassis/modules/monitor_1.py
volts/_status/monitors/0_start/status_1.py
volts/_status/monitors/1/stasis/path_1_health.py
volts/_status/monitors/1/stasis/path_2_health.py
volts/_status/monitors/1/status_1.py
volts/_status/monitors/2/stasis/1_health.py
volts/_status/monitors/2/stasis/2_health.py
volts/_status/monitors/2/stasis/modules/MODULE_1.py
volts/_status/monitors/2/status_1.py
volts/_status/monitors/3_empty_glob/status_1.py
volts/_status/monitors/4_bad_import/stasis/1_health.py
volts/_status/monitors/4_bad_import/status_1.py
volts/_status/monitors/5__file__/stasis/1_health.py
volts/_status/monitors/5__file__/stasis/MODULES/MODULE_1.py
volts/_status/monitors/5__file__/status_1.py
volts/_status/monitors/6_various/stasis/1_health.py
volts/_status/monitors/6_various/stasis/2_health.py
volts/_status/monitors/6_various/stasis/3_health.py
volts/_status/monitors/6_various/stasis/MODULES/MODULE_1.py
volts/_status/monitors/6_various/status_1.py
volts/_status/monitors/7/stasis/guarantee_1.py
volts/_status/monitors/7/status_1.py
volts/_status/monitors/8_DB/stasis/guarantee_1.py
volts/_status/monitors/8_DB/status_1.py
volts-1.1.1.dist-info/METADATA
volts-1.1.1.dist-info/WHEEL
volts-1.1.1.dist-info/entry_points.txt
volts-1.1.1.dist-info/RECORD
